metrics_render/__init__.py
metrics_render/app.py
metrics_render/config.py
metrics_render/debug.py
metrics_render/metrics_render.py
metrics_render-0.1.5.dist-info/entry_points.txt
metrics_render-0.1.5.dist-info/LICENSE
metrics_render-0.1.5.dist-info/WHEEL
metrics_render-0.1.5.dist-info/METADATA
metrics_render-0.1.5.dist-info/RECORD
