Metadata-Version: 2.1
Name: metrics-render
Version: 0.1.5
Summary: 
Author: laixintao
Author-email: laixintaoo@gmail.com
Requires-Python: >=3.9,<4.0
Classifier: Programming Language :: Python :: 3
Classifier: Programming Language :: Python :: 3.9
Classifier: Programming Language :: Python :: 3.10
Classifier: Programming Language :: Python :: 3.11
Requires-Dist: boto3 (>=1.25.3,<2.0.0)
Requires-Dist: click (>=8.1.3,<9.0.0)
Requires-Dist: flask (>=2.2.2,<3.0.0)
Requires-Dist: kaleido (==0.2.1)
Requires-Dist: minio (>=7.1.12,<8.0.0)
Requires-Dist: plotly (>=5.10.0,<6.0.0)
Requires-Dist: prometheus-client (>=0.15.0,<0.16.0)
Requires-Dist: promqlpy (>=1.0.5,<2.0.0)
Requires-Dist: requests (>=2.28.1,<3.0.0)
Requires-Dist: waitress (>=2.1.2,<3.0.0)
